Metadata-Version: 2.1
Name: levenshtein-coding
Version: 1.0.1
Summary: Python package implementing Levenshtein coding.
Home-page: https://github.com/LucaCappelletti94/levenshtein_coding
Author: Luca Cappelletti
Author-email: cappelletti.luca94@gmail.com
License: MIT
Platform: UNKNOWN
Classifier: Development Status :: 3 - Alpha
Classifier: License :: OSI Approved :: MIT License
Classifier: Programming Language :: Python :: 3
Provides-Extra: test
